Workbook

Sheet 1_Raw_Data
A1: Company | B1: Year | C1: Reporting_Standard | D1: Revenue_EUR | E1: EBIT_EUR | F1: CapEx_EUR | G1: RnD_EUR | H1: Total_Deliveries | I1: BEV_Deliveries | J1: Lithium_Price_USD
A2: BMW | B2: 2021 | C2: IFRS | D2: 111239 | E2: 16060 | F2: 5012 | G2: 6299 | H2: 2521514 | I2: 103855 | J2: 17000
A3: BMW | B3: 2022 | C3: IFRS | D3: 142610 | E3: 23509 | F3: 7179 | G3: 6624 | H3: 2399632 | I3: 215752 | J3: 70000
A4: BMW | B4: 2023 | C4: IFRS | D4: 155498 | E4: 17096 | F4: 8836 | G4: 7538 | H4: 2554183 | I4: 376183 | J4: 32000
A5: BMW | B5: 2024 | C5: IFRS | D5: 142380 | E5: 10236 | F5: 8500 | G5: 7400 | H5: 2450814 | I5: 375716 | J5: 14000
A6: BMW | B6: 2025 | C6: IFRS | D6: 133453 | E6: 9845 | F6: 8100 | G6: 7000 | H6: 2463681 | I6: 412350 | J6: 13500
A7: Mercedes-Benz | B7: 2021 | C7: IFRS | D7: 133893 | E7: 13974 | F7: 4600 | G7: 7700 | H7: 2330169 | I7: 99300 | J7: 17000
A8: Mercedes-Benz | B8: 2022 | C8: IFRS | D8: 150017 | E8: 20458 | F8: 5200 | G8: 8500 | H8: 2456700 | I8: 149200 | J8: 70000
A9: Mercedes-Benz | B9: 2023 | C9: IFRS | D9: 153218 | E9: 19683 | F9: 6300 | G9: 9200 | H9: 2491600 | I9: 240660 | J9: 32000
A10: Mercedes-Benz | B10: 2024 | C10: IFRS | D10: 149150 | E10: 14210 | F10: 6100 | G10: 9000 | H10: 2374200 | I10: 224100 | J10: 14000
A11: Mercedes-Benz | B11: 2025 | C11: IFRS | D11: 141800 | E11: 11350 | F11: 5800 | G11: 8600 | H11: 2351000 | I11: 201400 | J11: 13500
A12: Volkswagen | B12: 2021 | C12: IFRS | D12: 250200 | E12: 19275 | F12: 10500 | G12: 15600 | H12: 8882000 | I12: 452900 | J12: 17000
A13: Volkswagen | B13: 2022 | C13: IFRS | D13: 279232 | E13: 22124 | F13: 12700 | G13: 18900 | H13: 8262800 | I13: 572100 | J13: 70000
... A26: Tesla | B26: 2025 | C26: US-GAAP | D26: 97980 | E26: 8050 | F26: 8464 | G26: 4140 | H26: 2110400 | I26: 2110400 | J26: 13500

Sheet 2_KPI_Analysis
A1: Company | B1: Year | C1: Revenue (EUR) | D1: EBIT (EUR) | E1: Total Deliveries (Units) | F1: BEV Deliveries (Units) | G1: EBIT Margin % | H1: EV Mix % | I1: CapEx (EUR) | J1: CapEx Intensity % | K1: Revenue Growth (%) | L1: R&D EUR | M1: R&D Intensity %
A2: ='1_Raw_Data'!A2 -> BMW | B2: ='1_Raw_Data'!B2 -> 2021 | C2: =SUMIFS('1_Raw_Data'!D:D, '1_Raw_Data'!A:A, $A2, '1_Raw_Data'!B:B, $B2) -> 111239 | D2: =SUMIFS('1_Raw_Data'!E:E, '1_Raw_Data'!A:A, $A2, '1_Raw_Data'!B:B, $B2) -> 16060 | E2: =SUMIFS('1_Raw_Data'!H:H, '1_Raw_Data'!A:A, $A2, '1_Raw_Data'!B:B, $B2) -> 2521514 | F2: =SUMIFS('1_Raw_Data'!I:I, '1_Raw_Data'!A:A, $A2, '1_Raw_Data'!B:B, $B2) -> 103855 | G2: =D2/C2 -> 0.14437383 | H2: =F2/E2 -> 0.041187556 | I2: =SUMIFS('1_Raw_Data'!F:F, '1_Raw_Data'!A:A, $A2, '1_Raw_Data'!B:B, $B2) -> 5012 | J2: =I2/C2 -> 0.04505614 | K2: =IF($B2=2021, "N/A", (C2-C1)/C1) -> N/A | L2: =SUMIFS('1_Raw_Data'!G:G, '1_Raw_Data'!A:A, $A2, '1_Raw_Data'!B:B, $B2) -> 6299 | M2: =L2/C2 -> 0.056625824
A3: ='1_Raw_Data'!A3 -> BMW | B3: ='1_Raw_Data'!B3 -> 2022 | C3: =SUMIFS('1_Raw_Data'!D:D, '1_Raw_Data'!A:A, $A3, '1_Raw_Data'!B:B, $B3) -> 142610 | D3: =SUMIFS('1_Raw_Data'!E:E, '1_Raw_Data'!A:A, $A3, '1_Raw_Data'!B:B, $B3) -> 23509 | E3: =SUMIFS('1_Raw_Data'!H:H, '1_Raw_Data'!A:A, $A3, '1_Raw_Data'!B:B, $B3) -> 2399632 | F3: =SUMIFS('1_Raw_Data'!I:I, '1_Raw_Data'!A:A, $A3, '1_Raw_Data'!B:B, $B3) -> 215752 | G3: =D3/C3 -> 0.16484819 | H3: =F3/E3 -> 0.089910453 | I3: =SUMIFS('1_Raw_Data'!F:F, '1_Raw_Data'!A:A, $A3, '1_Raw_Data'!B:B, $B3) -> 7179 | J3: =I3/C3 -> 0.050340088 | K3: =IF($B3=2021, "N/A", (C3-C2)/C2) -> 0.2820144 | L3: =SUMIFS('1_Raw_Data'!G:G, '1_Raw_Data'!A:A, $A3, '1_Raw_Data'!B:B, $B3) -> 6624 | M3: =L3/C3 -> 0.046448356
A4: ='1_Raw_Data'!A4 -> BMW | B4: ='1_Raw_Data'!B4 -> 2023 | C4: =SUMIFS('1_Raw_Data'!D:D, '1_Raw_Data'!A:A, $A4, '1_Raw_Data'!B:B, $B4) -> 155498 | D4: =SUMIFS('1_Raw_Data'!E:E, '1_Raw_Data'!A:A, $A4, '1_Raw_Data'!B:B, $B4) -> 17096 | E4: =SUMIFS('1_Raw_Data'!H:H, '1_Raw_Data'!A:A, $A4, '1_Raw_Data'!B:B, $B4) -> 2554183 | F4: =SUMIFS('1_Raw_Data'!I:I, '1_Raw_Data'!A:A, $A4, '1_Raw_Data'!B:B, $B4) -> 376183 | G4: =D4/C4 -> 0.10994354 | H4: =F4/E4 -> 0.14728115 | I4: =SUMIFS('1_Raw_Data'!F:F, '1_Raw_Data'!A:A, $A4, '1_Raw_Data'!B:B, $B4) -> 8836 | J4: =I4/C4 -> 0.056823882 | K4: =IF($B4=2021, "N/A", (C4-C3)/C3) -> 0.090372344 | L4: =SUMIFS('1_Raw_Data'!G:G, '1_Raw_Data'!A:A, $A4, '1_Raw_Data'!B:B, $B4) -> 7538 | M4: =L4/C4 -> 0.048476508
A5: ='1_Raw_Data'!A5 -> BMW | B5: ='1_Raw_Data'!B5 -> 2024 | C5: =SUMIFS('1_Raw_Data'!D:D, '1_Raw_Data'!A:A, $A5, '1_Raw_Data'!B:B, $B5) -> 142380 | D5: =SUMIFS('1_Raw_Data'!E:E, '1_Raw_Data'!A:A, $A5, '1_Raw_Data'!B:B, $B5) -> 10236 | E5: =SUMIFS('1_Raw_Data'!H:H, '1_Raw_Data'!A:A, $A5, '1_Raw_Data'!B:B, $B5) -> 2450814 | F5: =SUMIFS('1_Raw_Data'!I:I, '1_Raw_Data'!A:A, $A5, '1_Raw_Data'!B:B, $B5) -> 375716 | G5: =D5/C5 -> 0.07189212 | H5: =F5/E5 -> 0.15330254 | I5: =SUMIFS('1_Raw_Data'!F:F, '1_Raw_Data'!A:A, $A5, '1_Raw_Data'!B:B, $B5) -> 8500 | J5: =I5/C5 -> 0.059699396 | K5: =IF($B5=2021, "N/A", (C5-C4)/C4) -> -0.084361214 | L5: =SUMIFS('1_Raw_Data'!G:G, '1_Raw_Data'!A:A, $A5, '1_Raw_Data'!B:B, $B5) -> 7400 | M5: =L5/C5 -> 0.051973592
A6: ='1_Raw_Data'!A6 -> BMW | B6: ='1_Raw_Data'!B6 -> 2025 | C6: =SUMIFS('1_Raw_Data'!D:D, '1_Raw_Data'!A:A, $A6, '1_Raw_Data'!B:B, $B6) -> 133453 | D6: =SUMIFS('1_Raw_Data'!E:E, '1_Raw_Data'!A:A, $A6, '1_Raw_Data'!B:B, $B6) -> 9845 | E6: =SUMIFS('1_Raw_Data'!H:H, '1_Raw_Data'!A:A, $A6, '1_Raw_Data'!B:B, $B6) -> 2463681 | F6: =SUMIFS('1_Raw_Data'!I:I, '1_Raw_Data'!A:A, $A6, '1_Raw_Data'!B:B, $B6) -> 412350 | G6: =D6/C6 -> 0.07377129 | H6: =F6/E6 -> 0.16737151 | I6: =SUMIFS('1_Raw_Data'!F:F, '1_Raw_Data'!A:A, $A6, '1_Raw_Data'!B:B, $B6) -> 8100 | J6: =I6/C6 -> 0.060695526 | K6: =IF($B6=2021, "N/A", (C6-C5)/C5) -> -0.062698413 | L6: =SUMIFS('1_Raw_Data'!G:G, '1_Raw_Data'!A:A, $A6, '1_Raw_Data'!B:B, $B6) -> 7000 | M6: =L6/C6 -> 0.052452924
A7: ='1_Raw_Data'!A7 -> Mercedes-Benz | B7: ='1_Raw_Data'!B7 -> 2021 | C7: =SUMIFS('1_Raw_Data'!D:D, '1_Raw_Data'!A:A, $A7, '1_Raw_Data'!B:B, $B7) -> 133893 | D7: =SUMIFS('1_Raw_Data'!E:E, '1_Raw_Data'!A:A, $A7, '1_Raw_Data'!B:B, $B7) -> 13974 | E7: =SUMIFS('1_Raw_Data'!H:H, '1_Raw_Data'!A:A, $A7, '1_Raw_Data'!B:B, $B7) -> 2330169 | F7: =SUMIFS('1_Raw_Data'!I:I, '1_Raw_Data'!A:A, $A7, '1_Raw_Data'!B:B, $B7) -> 99300 | G7: =D7/C7 -> 0.10436692 | H7: =F7/E7 -> 0.042614935 | I7: =SUMIFS('1_Raw_Data'!F:F, '1_Raw_Data'!A:A, $A7, '1_Raw_Data'!B:B, $B7) -> 4600 | J7: =I7/C7 -> 0.034355792 | K7: =IF($B7=2021, "N/A", (C7-C6)/C6) -> N/A | L7: =SUMIFS('1_Raw_Data'!G:G, '1_Raw_Data'!A:A, $A7, '1_Raw_Data'!B:B, $B7) -> 7700 | M7: =L7/C7 -> 0.057508608
A8: ='1_Raw_Data'!A8 -> Mercedes-Benz | B8: ='1_Raw_Data'!B8 -> 2022 | C8: =SUMIFS('1_Raw_Data'!D:D, '1_Raw_Data'!A:A, $A8, '1_Raw_Data'!B:B, $B8) -> 150017 | D8: =SUMIFS('1_Raw_Data'!E:E, '1_Raw_Data'!A:A, $A8, '1_Raw_Data'!B:B, $B8) -> 20458 | E8: =SUMIFS('1_Raw_Data'!H:H, '1_Raw_Data'!A:A, $A8, '1_Raw_Data'!B:B, $B8) -> 2456700 | F8: =SUMIFS('1_Raw_Data'!I:I, '1_Raw_Data'!A:A, $A8, '1_Raw_Data'!B:B, $B8) -> 149200 | G8: =D8/C8 -> 0.13637121 | H8: =F8/E8 -> 0.060731876 | I8: =SUMIFS('1_Raw_Data'!F:F, '1_Raw_Data'!A:A, $A8, '1_Raw_Data'!B:B, $B8) -> 5200 | J8: =I8/C8 -> 0.034662738 | K8: =IF($B8=2021, "N/A", (C8-C7)/C7) -> 0.12042452 | L8: =SUMIFS('1_Raw_Data'!G:G, '1_Raw_Data'!A:A, $A8, '1_Raw_Data'!B:B, $B8) -> 8500 | M8: =L8/C8 -> 0.056660245
A9: ='1_Raw_Data'!A9 -> Mercedes-Benz | B9: ='1_Raw_Data'!B9 -> 2023 | C9: =SUMIFS('1_Raw_Data'!D:D, '1_Raw_Data'!A:A, $A9, '1_Raw_Data'!B:B, $B9) -> 153218 | D9: =SUMIFS('1_Raw_Data'!E:E, '1_Raw_Data'!A:A, $A9, '1_Raw_Data'!B:B, $B9) -> 19683 | E9: =SUMIFS('1_Raw_Data'!H:H, '1_Raw_Data'!A:A, $A9, '1_Raw_Data'!B:B, $B9) -> 2491600 | F9: =SUMIFS('1_Raw_Data'!I:I, '1_Raw_Data'!A:A, $A9, '1_Raw_Data'!B:B, $B9) -> 240660 | G9: =D9/C9 -> 0.12846402 | H9: =F9/E9 -> 0.096588537 | I9: =SUMIFS('1_Raw_Data'!F:F, '1_Raw_Data'!A:A, $A9, '1_Raw_Data'!B:B, $B9) -> 6300 | J9: =I9/C9 -> 0.041117884 | K9: =IF($B9=2021, "N/A", (C9-C8)/C8) -> 0.021337582 | L9: =SUMIFS('1_Raw_Data'!G:G, '1_Raw_Data'!A:A, $A9, '1_Raw_Data'!B:B, $B9) -> 9200 | M9: =L9/C9 -> 0.060045164
A10: ='1_Raw_Data'!A10 -> Mercedes-Benz | B10: ='1_Raw_Data'!B10 -> 2024 | C10: =SUMIFS('1_Raw_Data'!D:D, '1_Raw_Data'!A:A, $A10, '1_Raw_Data'!B:B, $B10) -> 149150 | D10: =SUMIFS('1_Raw_Data'!E:E, '1_Raw_Data'!A:A, $A10, '1_Raw_Data'!B:B, $B10) -> 14210 | E10: =SUMIFS('1_Raw_Data'!H:H, '1_Raw_Data'!A:A, $A10, '1_Raw_Data'!B:B, $B10) -> 2374200 | F10: =SUMIFS('1_Raw_Data'!I:I, '1_Raw_Data'!A:A, $A10, '1_Raw_Data'!B:B, $B10) -> 224100 | G10: =D10/C10 -> 0.095273215 | H10: =F10/E10 -> 0.094389689 | I10: =SUMIFS('1_Raw_Data'!F:F, '1_Raw_Data'!A:A, $A10, '1_Raw_Data'!B:B, $B10) -> 6100 | J10: =I10/C10 -> 0.040898424 | K10: =IF($B10=2021, "N/A", (C10-C9)/C9) -> -0.026550405 | L10: =SUMIFS('1_Raw_Data'!G:G, '1_Raw_Data'!A:A, $A10, '1_Raw_Data'!B:B, $B10) -> 9000 | M10: =L10/C10 -> 0.060341938
A11: ='1_Raw_Data'!A11 -> Mercedes-Benz | B11: ='1_Raw_Data'!B11 -> 2025 | C11: =SUMIFS('1_Raw_Data'!D:D, '1_Raw_Data'!A:A, $A11, '1_Raw_Data'!B:B, $B11) -> 141800 | D11: =SUMIFS('1_Raw_Data'!E:E, '1_Raw_Data'!A:A, $A11, '1_Raw_Data'!B:B, $B11) -> 11350 | E11: =SUMIFS('1_Raw_Data'!H:H, '1_Raw_Data'!A:A, $A11, '1_Raw_Data'!B:B, $B11) -> 2351000 | F11: =SUMIFS('1_Raw_Data'!I:I, '1_Raw_Data'!A:A, $A11, '1_Raw_Data'!B:B, $B11) -> 201400 | G11: =D11/C11 -> 0.080042313 | H11: =F11/E11 -> 0.085665674 | I11: =SUMIFS('1_Raw_Data'!F:F, '1_Raw_Data'!A:A, $A11, '1_Raw_Data'!B:B, $B11) -> 5800 | J11: =I11/C11 -> 0.04090268 | K11: =IF($B11=2021, "N/A", (C11-C10)/C10) -> -0.049279249 | L11: =SUMIFS('1_Raw_Data'!G:G, '1_Raw_Data'!A:A, $A11, '1_Raw_Data'!B:B, $B11) -> 8600 | M11: =L11/C11 -> 0.060648801
A12: ='1_Raw_Data'!A12 -> Volkswagen | B12: ='1_Raw_Data'!B12 -> 2021 | C12: =SUMIFS('1_Raw_Data'!D:D, '1_Raw_Data'!A:A, $A12, '1_Raw_Data'!B:B, $B12) -> 250200 | D12: =SUMIFS('1_Raw_Data'!E:E, '1_Raw_Data'!A:A, $A12, '1_Raw_Data'!B:B, $B12) -> 19275 | E12: =SUMIFS('1_Raw_Data'!H:H, '1_Raw_Data'!A:A, $A12, '1_Raw_Data'!B:B, $B12) -> 8882000 | F12: =SUMIFS('1_Raw_Data'!I:I, '1_Raw_Data'!A:A, $A12, '1_Raw_Data'!B:B, $B12) -> 452900 | G12: =D12/C12 -> 0.077038369 | H12: =F12/E12 -> 0.050990768 | I12: =SUMIFS('1_Raw_Data'!F:F, '1_Raw_Data'!A:A, $A12, '1_Raw_Data'!B:B, $B12) -> 10500 | J12: =I12/C12 -> 0.041966427 | K12: =IF($B12=2021, "N/A", (C12-C11)/C11) -> N/A | L12: =SUMIFS('1_Raw_Data'!G:G, '1_Raw_Data'!A:A, $A12, '1_Raw_Data'!B:B, $B12) -> 15600 | M12: =L12/C12 -> 0.06235012
A13: ='1_Raw_Data'!A13 -> Volkswagen | B13: ='1_Raw_Data'!B13 -> 2022 | C13: =SUMIFS('1_Raw_Data'!D:D, '1_Raw_Data'!A:A, $A13, '1_Raw_Data'!B:B, $B13) -> 279232 | D13: =SUMIFS('1_Raw_Data'!E:E, '1_Raw_Data'!A:A, $A13, '1_Raw_Data'!B:B, $B13) -> 22124 | E13: =SUMIFS('1_Raw_Data'!H:H, '1_Raw_Data'!A:A, $A13, '1_Raw_Data'!B:B, $B13) -> 8262800 | F13: =SUMIFS('1_Raw_Data'!I:I, '1_Raw_Data'!A:A, $A13, '1_Raw_Data'!B:B, $B13) -> 572100 | G13: =D13/C13 -> 0.079231607 | H13: =F13/E13 -> 0.069238031 | I13: =SUMIFS('1_Raw_Data'!F:F, '1_Raw_Data'!A:A, $A13, '1_Raw_Data'!B:B, $B13) -> 12700 | J13: =I13/C13 -> 0.045481893 | K13: =IF($B13=2021, "N/A", (C13-C12)/C12) -> 0.11603517 | L13: =SUMIFS('1_Raw_Data'!G:G, '1_Raw_Data'!A:A, $A13, '1_Raw_Data'!B:B, $B13) -> 18900 | M13: =L13/C13 -> 0.067685652
... A26: ='1_Raw_Data'!A26 -> Tesla | B26: ='1_Raw_Data'!B26 -> 2025 | C26: =SUMIFS('1_Raw_Data'!D:D, '1_Raw_Data'!A:A, $A26, '1_Raw_Data'!B:B, $B26) -> 97980 | D26: =SUMIFS('1_Raw_Data'!E:E, '1_Raw_Data'!A:A, $A26, '1_Raw_Data'!B:B, $B26) -> 8050 | E26: =SUMIFS('1_Raw_Data'!H:H, '1_Raw_Data'!A:A, $A26, '1_Raw_Data'!B:B, $B26) -> 2110400 | F26: =SUMIFS('1_Raw_Data'!I:I, '1_Raw_Data'!A:A, $A26, '1_Raw_Data'!B:B, $B26) -> 2110400 | G26: =D26/C26 -> 0.082159624 | H26: =F26/E26 -> 1 | I26: =SUMIFS('1_Raw_Data'!F:F, '1_Raw_Data'!A:A, $A26, '1_Raw_Data'!B:B, $B26) -> 8464 | J26: =I26/C26 -> 0.086384977 | K26: =IF($B26=2021, "N/A", (C26-C25)/C25) -> 0.081218274 | L26: =SUMIFS('1_Raw_Data'!G:G, '1_Raw_Data'!A:A, $A26, '1_Raw_Data'!B:B, $B26) -> 4140 | M26: =L26/C26 -> 0.042253521

Sheet 3_Pivot_Analysis
A3: Average of EBIT Margin % | B3: Column Labels | I3: Average of EV Mix % | J3: Column Labels
A4: Row Labels | B4: 2021 | C4: 2022 | D4: 2023 | E4: 2024 | F4: 2025 | G4: Grand Total | I4: Row Labels | J4: 2021 | K4: 2022 | L4: 2023 | M4: 2024 | N4: 2025 | O4: Grand Total
A5: BMW | B5: 0.14437383 | C5: 0.16484819 | D5: 0.10994354 | E5: 0.07189212 | F5: 0.07377129 | G5: 0.11296579 | I5: BMW | J5: 0.041187556 | K5: 0.089910453 | L5: 0.14728115 | M5: 0.15330254 | N5: 0.16737151 | O5: 0.11981064
A6: Mercedes-Benz | B6: 0.10436692 | C6: 0.13637121 | D6: 0.12846402 | E6: 0.095273215 | F6: 0.080042313 | G6: 0.10890354 | I6: Mercedes-Benz | J6: 0.042614935 | K6: 0.060731876 | L6: 0.096588537 | M6: 0.094389689 | N6: 0.085665674 | O6: 0.075998142
A7: Porsche | B7: 0.16035971 | C7: 0.17990965 | D7: 0.17971873 | E7: 0.13790505 | F7: 0.12779802 | G7: 0.15713823 | I7: Porsche | J7: 0.13678022 | K7: 0.11230331 | L7: 0.126878 | M7: 0.10797175 | N7: 0.15883362 | O7: 0.12855338
A8: Tesla | B8: 0.12119354 | C8: 0.16763644 | D8: 0.0918748 | E8: 0.075126904 | F8: 0.082159624 | G8: 0.10759826 | I8: Tesla | J8: 1 | K8: 1 | L8: 1 | M8: 1 | N8: 1 | O8: 1
A9: Volkswagen | B9: 0.077038369 | C9: 0.079231607 | D9: 0.070050018 | E9: 0.058708294 | F9: 0.027547816 | G9: 0.062515221 | I9: Volkswagen | J9: 0.050990768 | K9: 0.069238031 | L9: 0.083456897 | M9: 0.083441558 | N9: 0.079329609 | O9: 0.073291373
A10: Grand Total | B10: 0.12146647 | C10: 0.14559942 | D10: 0.11601022 | E10: 0.087781116 | F10: 0.078263813 | G10: 0.10982421 | I10: Grand Total | J10: 0.2543147 | K10: 0.26643673 | L10: 0.29084092 | M10: 0.28782111 | N10: 0.29824008 | O10: 0.27953071
A17: Average of Revenue (EUR) | B17: Column Labels | I17: Average of CapEx Intensity % | J17: Column Labels
A18: Row Labels | B18: 2021 | C18: 2022 | D18: 2023 | E18: 2024 | F18: 2025 | G18: Grand Total | I18: Row Labels | J18: 2021 | K18: 2022 | L18: 2023 | M18: 2024 | N18: 2025 | O18: Grand Total
A19: BMW | B19: 111239 | C19: 142610 | D19: 155498 | E19: 142380 | F19: 133453 | G19: 137036 | I19: BMW | J19: 0.04505614 | K19: 0.050340088 | L19: 0.056823882 | M19: 0.059699396 | N19: 0.060695526 | O19: 0.054523006
A20: Mercedes-Benz | B20: 133893 | C20: 150017 | D20: 153218 | E20: 149150 | F20: 141800 | G20: 145615.6 | I20: Mercedes-Benz | J20: 0.034355792 | K20: 0.034662738 | L20: 0.041117884 | M20: 0.040898424 | N20: 0.04090268 | O20: 0.038387504
A21: Porsche | B21: 33138 | C21: 37630 | D21: 40530 | E21: 39810 | F21: 38420 | G21: 37905.6 | I21: Porsche | J21: 0.042247571 | K21: 0.047834175 | L21: 0.05428078 | M21: 0.052750565 | N21: 0.052056221 | O21: 0.049833862
A22: Tesla | B22: 49517.16 | C22: 74945.04 | D22: 89031.16 | E22: 90620 | F22: 97980 | G22: 80418.672 | I22: Tesla | J22: 0.12043179 | K22: 0.087869191 | L22: 0.091957467 | M22: 0.086294416 | N22: 0.086384977 | O22: 0.094587567
A23: Volkswagen | B23: 250200 | C23: 279232 | D23: 322284 | E23: 324656 | F23: 321913 | G23: 299657 | I23: Volkswagen | J23: 0.041966427 | K23: 0.045481893 | L23: 0.05057651 | M23: 0.048666897 | N23: 0.046596441 | O23: 0.046657634
A24: Grand Total | B24: 115597.43 | C24: 136886.81 | D24: 152112.23 | E24: 149323.2 | F24: 146713.2 | G24: 140126.57 | I24: Grand Total | J24: 0.056811543 | K24: 0.053237617 | L24: 0.058951305 | M24: 0.05766194 | N24: 0.057327169 | O24: 0.056797915

Sheet 4_Strategic_Analysis
B1: CORE STRATEGIC INQUIRY: Which manufacturer is executing the EV transition most effectively while maintaining operational profitability?
B3: EV Adoption Velocity
B4: BMW led the legacy OEM transition, aggressively expanding its EV mix from 4.1% to 16.7% (2021–2025). Tesla maintained a pure-play 100% BEV baseline, acting as the industry benchmark.
B6: Margin Retention vs. Transition
B7: BMW successfully utilized flexible manufacturing architectures (producing ICE and BEV on shared lines) to scale EV production while minimizing EBIT margin compression, outperforming Mercedes-Benz in baseline margin retention by 2025.
B9: Capital Intensity & Scale
B10: Volkswagen executed the most capital-intensive transition, pushing CapEx intensity up to 4.6% to completely overhaul legacy architectures and build dedicated battery infrastructure. This heavy investment cycle directly correlated with a margin contraction to 2.7% by 2025, prioritizing long-term scale over short-term profitability.
B12: Conclusion
B13: BMW appears to demonstrate one of the most balanced EV transition strategies among legacy OEMs, combining rising EV penetration with relatively resilient operating margins.

Sheet 5_Scenario_Analysis
B2: Model Assumption: | C2: Battery pack cost accounts for 35% of total manufacturing cost (COGS): | D2: 0.35
B3: Source (inspiration for scenario): | C3: McKinsey Center for Future Mobility (Battery Pack Cost Breakthroughs)
B5: Target Company: | C5: BMW (2025 Baseline)
B6: Baseline EBIT Margin: | C6: ='2_KPI_Analysis'!G6 -> 0.07377129
B7: %change in
B9: Battery Cost Shift | C9: Market Scenario | D9: Adjusted EBIT Margin (%)
B10: -0.3 | C10: Breakthrough (LFP/Solid State) | D10: =$C$6 - (B10 * $D$2) -> 0.17877129
B11: -0.15 | C11: Scale Efficiencies Achieved | D11: =$C$6 - (B11 * $D$2) -> 0.12627129
B12: 0 | C12: Current Baseline | D12: =$C$6 - (B12 * $D$2) -> 0.07377129
B13: 0.15 | C13: Raw Material Shortage | D13: =$C$6 - (B13 * $D$2) -> 0.02127129
B14: 0.3 | C14: Global Supply Chain Crisis | D14: =$C$6 - (B14 * $D$2) -> -0.03122871
